{                                                                                                                                                                                                                                                              
	"d": {                                                                                                                                                                                                                                                        
		"results": [{                                                                                                                                                                                                                                                
			"KNRZE": "MG001_HO",                                                                                                                                                                                                                                        
			"MCOD1": "GRÜNEWALD BRANCH",                                                                                                                                                                                                                                
			"MCOD3": "WIESENBACH",                                                                                                                                                                                                                                      
			"KUNNR": "MG001_BR",                                                                                                                                                                                                                                        
			"BUKRS": "0001"                                                                                                                                                                                                                                             
		}]                                                                                                                                                                                                                                                           
	}                                                                                                                                                                                                                                                             
}                                                                                                                                                                                                                                                              